{
  "fio version" : "fio-3.39-28-gd2a4",
  "timestamp" : 1742520313,
  "timestamp_ms" : 1742520313494,
  "time" : "Thu Mar 20 18:25:13 2025",
  "jobs" : [
    {
      "jobname" : "FIOJOB",
      "groupid" : 0,
      "job_start" : 1742520133367,
      "error" : 0,
      "eta" : 0,
      "elapsed" : 181,
      "job options" : {
        "ioengine" : "libaio",
        "rw" : "randwrite",
        "size" : "10G",
        "bs" : "4k",
        "iodepth" : "8",
        "numjobs" : "1",
        "runtime" : "180",
        "loops" : "1",
        "direct" : "1",
        "log_avg_msec" : "1000",
        "invalidate" : "1",
        "write_bw_log" : "../azuredisks/nvme0n10/4k/randwrite-iodepth-8-numjobs-1",
        "write_lat_log" : "../azuredisks/nvme0n10/4k/randwrite-iodepth-8-numjobs-1",
        "write_iops_log" : "../azuredisks/nvme0n10/4k/randwrite-iodepth-8-numjobs-1",
        "filename" : "/dev/nvme0n10"
      },
      "read" : {
        "io_bytes" : 0,
        "io_kbytes" : 0,
        "bw_bytes" : 0,
        "bw" : 0,
        "iops" : 0.000000,
        "runtime" : 0,
        "total_ios" : 0,
        "short_ios" : 0,
        "drop_ios" : 0,
        "slat_ns" : {
          "min" : 0,
          "max" : 0,
          "mean" : 0.000000,
          "stddev" : 0.000000,
          "N" : 0
        },
        "clat_ns" : {
          "min" : 0,
          "max" : 0,
          "mean" : 0.000000,
          "stddev" : 0.000000,
          "N" : 0
        },
        "lat_ns" : {
          "min" : 0,
          "max" : 0,
          "mean" : 0.000000,
          "stddev" : 0.000000,
          "N" : 0
        },
        "bw_min" : 0,
        "bw_max" : 0,
        "bw_agg" : 0.000000,
        "bw_mean" : 0.000000,
        "bw_dev" : 0.000000,
        "bw_samples" : 0,
        "iops_min" : 0,
        "iops_max" : 0,
        "iops_mean" : 0.000000,
        "iops_stddev" : 0.000000,
        "iops_samples" : 0
      },
      "write" : {
        "io_bytes" : 6470520832,
        "io_kbytes" : 6318868,
        "bw_bytes" : 35947138,
        "bw" : 35104,
        "iops" : 8776.156799,
        "runtime" : 180001,
        "total_ios" : 1579717,
        "short_ios" : 0,
        "drop_ios" : 0,
        "slat_ns" : {
          "min" : 1014,
          "max" : 123630,
          "mean" : 1653.820899,
          "stddev" : 1276.605400,
          "N" : 1579717
        },
        "clat_ns" : {
          "min" : 559943,
          "max" : 123064199,
          "mean" : 909407.755649,
          "stddev" : 617708.911026,
          "N" : 1579717,
          "percentile" : {
            "1.000000" : 651264,
            "5.000000" : 684032,
            "10.000000" : 708608,
            "20.000000" : 733184,
            "30.000000" : 749568,
            "40.000000" : 774144,
            "50.000000" : 798720,
            "60.000000" : 823296,
            "70.000000" : 864256,
            "80.000000" : 921600,
            "90.000000" : 1105920,
            "95.000000" : 1482752,
            "99.000000" : 2834432,
            "99.500000" : 3686400,
            "99.900000" : 6717440,
            "99.950000" : 8585216,
            "99.990000" : 16187392
          }
        },
        "lat_ns" : {
          "min" : 561218,
          "max" : 123065650,
          "mean" : 911061.576548,
          "stddev" : 617732.978071,
          "N" : 1579717
        },
        "bw_min" : 30134,
        "bw_max" : 36900,
        "bw_agg" : 100.000000,
        "bw_mean" : 35123.983333,
        "bw_dev" : 1037.715796,
        "bw_samples" : 180,
        "iops_min" : 7533,
        "iops_max" : 9225,
        "iops_mean" : 8780.750000,
        "iops_stddev" : 259.497169,
        "iops_samples" : 180
      },
      "trim" : {
        "io_bytes" : 0,
        "io_kbytes" : 0,
        "bw_bytes" : 0,
        "bw" : 0,
        "iops" : 0.000000,
        "runtime" : 0,
        "total_ios" : 0,
        "short_ios" : 0,
        "drop_ios" : 0,
        "slat_ns" : {
          "min" : 0,
          "max" : 0,
          "mean" : 0.000000,
          "stddev" : 0.000000,
          "N" : 0
        },
        "clat_ns" : {
          "min" : 0,
          "max" : 0,
          "mean" : 0.000000,
          "stddev" : 0.000000,
          "N" : 0
        },
        "lat_ns" : {
          "min" : 0,
          "max" : 0,
          "mean" : 0.000000,
          "stddev" : 0.000000,
          "N" : 0
        },
        "bw_min" : 0,
        "bw_max" : 0,
        "bw_agg" : 0.000000,
        "bw_mean" : 0.000000,
        "bw_dev" : 0.000000,
        "bw_samples" : 0,
        "iops_min" : 0,
        "iops_max" : 0,
        "iops_mean" : 0.000000,
        "iops_stddev" : 0.000000,
        "iops_samples" : 0
      },
      "sync" : {
        "total_ios" : 0,
        "lat_ns" : {
          "min" : 0,
          "max" : 0,
          "mean" : 0.000000,
          "stddev" : 0.000000,
          "N" : 0
        }
      },
      "job_runtime" : 180000,
      "usr_cpu" : 1.389444,
      "sys_cpu" : 4.069444,
      "ctx" : 1459842,
      "majf" : 0,
      "minf" : 244,
      "iodepth_level" : {
        "1" : 0.100000,
        "2" : 0.100000,
        "4" : 0.100000,
        "8" : 99.999557,
        "16" : 0.000000,
        "32" : 0.000000,
        ">=64" : 0.000000
      },
      "iodepth_submit" : {
        "0" : 0.000000,
        "4" : 100.000000,
        "8" : 0.000000,
        "16" : 0.000000,
        "32" : 0.000000,
        "64" : 0.000000,
        ">=64" : 0.000000
      },
      "iodepth_complete" : {
        "0" : 0.000000,
        "4" : 99.999937,
        "8" : 0.100000,
        "16" : 0.000000,
        "32" : 0.000000,
        "64" : 0.000000,
        ">=64" : 0.000000
      },
      "latency_ns" : {
        "2" : 0.000000,
        "4" : 0.000000,
        "10" : 0.000000,
        "20" : 0.000000,
        "50" : 0.000000,
        "100" : 0.000000,
        "250" : 0.000000,
        "500" : 0.000000,
        "750" : 0.000000,
        "1000" : 0.000000
      },
      "latency_us" : {
        "2" : 0.000000,
        "4" : 0.000000,
        "10" : 0.000000,
        "20" : 0.000000,
        "50" : 0.000000,
        "100" : 0.000000,
        "250" : 0.000000,
        "500" : 0.000000,
        "750" : 28.515171,
        "1000" : 57.361477
      },
      "latency_ms" : {
        "2" : 11.593026,
        "4" : 2.125824,
        "10" : 0.370066,
        "20" : 0.029815,
        "50" : 0.010000,
        "100" : 0.010000,
        "250" : 0.010000,
        "500" : 0.000000,
        "750" : 0.000000,
        "1000" : 0.000000,
        "2000" : 0.000000,
        ">=2000" : 0.000000
      },
      "latency_depth" : 8,
      "latency_target" : 0,
      "latency_percentile" : 100.000000,
      "latency_window" : 0
    }
  ],
  "disk_util" : [
    {
      "name" : "nvme0n10",
      "read_ios" : 40,
      "write_ios" : 1578682,
      "read_sectors" : 2024,
      "write_sectors" : 12629456,
      "read_merges" : 0,
      "write_merges" : 0,
      "read_ticks" : 65,
      "write_ticks" : 1429160,
      "in_queue" : 1429225,
      "util" : 100.000000
    }
  ]
}
